{
    "name": "randomcase_seed32_size100_100_100_pipes200_150_fill01",
    "size": [
        100,
        100,
        100
    ],
    "obstacles": [
        [
            40,
            17,
            98,
            70,
            70,
            100
        ],
        [
            72,
            81,
            9,
            82,
            89,
            95
        ],
        [
            0,
            32,
            64,
            82,
            71,
            68
        ],
        [
            84,
            72,
            66,
            94,
            99,
            82
        ],
        [
            1,
            15,
            0,
            6,
            47,
            48
        ],
        [
            59,
            62,
            36,
            63,
            93,
            48
        ],
        [
            7,
            19,
            30,
            53,
            45,
            41
        ],
        [
            10,
            79,
            19,
            49,
            100,
            98
        ]
    ],
    "pipes": [
        {
            "id": 1,
            "diameter": 1,
            "costs": 1,
            "connected_components": [
                {
                    "id": 1,
                    "terminals": [
                        [
                            87,
                            43,
                            5
                        ],
                        [
                            29,
                            5,
                            99
                        ]
                    ],
                    "forbidden_nodes": []
                }
            ]
        },
        {
            "id": 2,
            "diameter": 1,
            "costs": 1,
            "connected_components": [
                {
                    "id": 2,
                    "terminals": [
                        [
                            18,
                            78,
                            25
                        ],
                        [
                            97,
                            78,
                            96
                        ]
                    ],
                    "forbidden_nodes": []
                }
            ]
        }
    ]
}