{
    "name": "randomcase_seed32_size100_100_100_pipes200_150_fill02",
    "size": [
        100,
        100,
        100
    ],
    "obstacles": [
        [
            40,
            17,
            98,
            70,
            70,
            100
        ],
        [
            72,
            81,
            9,
            82,
            89,
            95
        ],
        [
            0,
            32,
            64,
            82,
            71,
            68
        ],
        [
            84,
            72,
            66,
            94,
            99,
            82
        ],
        [
            1,
            15,
            0,
            6,
            47,
            48
        ],
        [
            59,
            62,
            36,
            63,
            93,
            48
        ],
        [
            7,
            19,
            30,
            53,
            45,
            41
        ],
        [
            10,
            79,
            19,
            49,
            100,
            98
        ],
        [
            16,
            26,
            85,
            79,
            74,
            93
        ],
        [
            49,
            2,
            32,
            51,
            15,
            70
        ],
        [
            47,
            24,
            21,
            81,
            76,
            30
        ],
        [
            39,
            27,
            56,
            82,
            32,
            73
        ],
        [
            85,
            11,
            20,
            88,
            41,
            42
        ],
        [
            61,
            2,
            9,
            66,
            14,
            14
        ],
        [
            77,
            8,
            5,
            84,
            17,
            7
        ],
        [
            72,
            14,
            36,
            79,
            71,
            43
        ],
        [
            63,
            52,
            3,
            84,
            75,
            5
        ],
        [
            6,
            23,
            7,
            30,
            81,
            18
        ],
        [
            43,
            7,
            1,
            46,
            38,
            22
        ],
        [
            95,
            10,
            20,
            98,
            70,
            36
        ],
        [
            38,
            54,
            6,
            39,
            75,
            34
        ],
        [
            38,
            40,
            72,
            96,
            67,
            77
        ],
        [
            31,
            45,
            96,
            60,
            75,
            97
        ],
        [
            51,
            0,
            33,
            76,
            2,
            68
        ],
        [
            59,
            93,
            79,
            80,
            98,
            91
        ],
        [
            23,
            17,
            51,
            75,
            20,
            53
        ],
        [
            3,
            2,
            50,
            22,
            24,
            65
        ]
    ],
    "pipes": [
        {
            "id": 1,
            "diameter": 1,
            "costs": 1,
            "connected_components": [
                {
                    "id": 1,
                    "terminals": [
                        [
                            87,
                            43,
                            5
                        ],
                        [
                            29,
                            5,
                            99
                        ]
                    ],
                    "forbidden_nodes": []
                }
            ]
        },
        {
            "id": 2,
            "diameter": 1,
            "costs": 1,
            "connected_components": [
                {
                    "id": 2,
                    "terminals": [
                        [
                            18,
                            78,
                            25
                        ],
                        [
                            97,
                            78,
                            96
                        ]
                    ],
                    "forbidden_nodes": []
                }
            ]
        }
    ]
}