{
    "name": "randomcase_seed17_size100_100_100_pipes200_150_fill02",
    "size": [
        100,
        100,
        100
    ],
    "obstacles": [
        [
            57,
            83,
            46,
            66,
            90,
            73
        ],
        [
            3,
            24,
            75,
            76,
            76,
            79
        ],
        [
            47,
            16,
            4,
            52,
            89,
            60
        ],
        [
            26,
            9,
            35,
            70,
            15,
            55
        ],
        [
            21,
            20,
            8,
            43,
            31,
            10
        ],
        [
            54,
            23,
            1,
            70,
            47,
            42
        ],
        [
            72,
            34,
            27,
            93,
            69,
            28
        ],
        [
            64,
            59,
            11,
            79,
            93,
            14
        ],
        [
            25,
            16,
            80,
            78,
            31,
            87
        ],
        [
            82,
            5,
            5,
            100,
            16,
            30
        ],
        [
            16,
            57,
            16,
            38,
            63,
            34
        ],
        [
            4,
            20,
            20,
            15,
            24,
            67
        ],
        [
            15,
            22,
            23,
            29,
            49,
            41
        ],
        [
            3,
            70,
            3,
            29,
            84,
            66
        ],
        [
            63,
            79,
            5,
            89,
            95,
            6
        ],
        [
            39,
            77,
            20,
            46,
            100,
            75
        ],
        [
            7,
            38,
            27,
            10,
            56,
            72
        ],
        [
            94,
            38,
            21,
            97,
            75,
            52
        ],
        [
            54,
            78,
            1,
            62,
            96,
            27
        ],
        [
            72,
            12,
            89,
            93,
            57,
            100
        ],
        [
            62,
            8,
            56,
            100,
            23,
            77
        ],
        [
            11,
            57,
            90,
            29,
            60,
            96
        ],
        [
            18,
            49,
            80,
            87,
            72,
            82
        ],
        [
            44,
            4,
            16,
            72,
            8,
            83
        ],
        [
            74,
            2,
            1,
            80,
            23,
            26
        ],
        [
            9,
            92,
            17,
            23,
            94,
            98
        ],
        [
            8,
            4,
            96,
            66,
            33,
            97
        ],
        [
            3,
            9,
            15,
            13,
            10,
            20
        ],
        [
            78,
            72,
            83,
            88,
            100,
            95
        ],
        [
            66,
            40,
            64,
            69,
            70,
            65
        ],
        [
            84,
            38,
            68,
            88,
            40,
            72
        ],
        [
            74,
            2,
            37,
            80,
            85,
            55
        ],
        [
            4,
            13,
            7,
            18,
            19,
            8
        ],
        [
            67,
            66,
            66,
            99,
            88,
            69
        ],
        [
            42,
            37,
            82,
            53,
            92,
            94
        ],
        [
            78,
            59,
            82,
            92,
            70,
            100
        ],
        [
            33,
            5,
            75,
            35,
            10,
            91
        ],
        [
            43,
            42,
            61,
            59,
            50,
            69
        ],
        [
            2,
            24,
            43,
            6,
            45,
            44
        ],
        [
            2,
            0,
            69,
            39,
            17,
            71
        ],
        [
            2,
            25,
            58,
            33,
            31,
            64
        ],
        [
            73,
            4,
            28,
            76,
            87,
            36
        ],
        [
            55,
            22,
            45,
            58,
            79,
            49
        ],
        [
            37,
            18,
            2,
            50,
            38,
            3
        ],
        [
            95,
            2,
            42,
            100,
            11,
            47
        ],
        [
            3,
            2,
            14,
            36,
            5,
            20
        ],
        [
            79,
            28,
            15,
            84,
            70,
            23
        ],
        [
            30,
            84,
            27,
            36,
            100,
            94
        ]
    ],
    "pipes": [
        {
            "id": 1,
            "diameter": 1,
            "costs": 1,
            "connected_components": [
                {
                    "id": 1,
                    "terminals": [
                        [
                            15,
                            6,
                            22
                        ],
                        [
                            59,
                            61,
                            95
                        ]
                    ],
                    "forbidden_nodes": []
                }
            ]
        },
        {
            "id": 2,
            "diameter": 1,
            "costs": 1,
            "connected_components": [
                {
                    "id": 2,
                    "terminals": [
                        [
                            56,
                            50,
                            1
                        ],
                        [
                            17,
                            16,
                            68
                        ]
                    ],
                    "forbidden_nodes": []
                }
            ]
        }
    ]
}